datawake_logger/enums.py
datawake_logger/init.py
datawake_logger/logger.py
datawake_logger-1.0.1.dist-info/licenses/LICENSE
datawake_logger-1.0.1.dist-info/METADATA
datawake_logger-1.0.1.dist-info/WHEEL
datawake_logger-1.0.1.dist-info/top_level.txt
datawake_logger-1.0.1.dist-info/RECORD
