Metadata-Version: 2.4
Name: datawake-logger
Version: 1.0.1
Summary: Cliente assíncrono para envio de logs para a API DataWake
Author-email: DataWake Team <contato@datawake.cloud>
License: MIT
Project-URL: Homepage, https://github.com/datawake/datawake-logger
Project-URL: Documentation, https://github.com/datawake/datawake-logger/blob/main/README.md
Project-URL: Repository, https://github.com/datawake/datawake-logger
Project-URL: Bug Tracker, https://github.com/datawake/datawake-logger/issues
Keywords: logging,async,api,datawake
Classifier: Development Status :: 4 - Beta
Classifier: Intended Audience :: Developers
Classifier: License :: OSI Approved :: MIT License
Classifier: Programming Language :: Python :: 3
Classifier: Programming Language :: Python :: 3.8
Classifier: Programming Language :: Python :: 3.9
Classifier: Programming Language :: Python :: 3.10
Classifier: Programming Language :: Python :: 3.11
Classifier: Programming Language :: Python :: 3.12
Classifier: Topic :: Software Development :: Libraries :: Python Modules
Classifier: Topic :: System :: Logging
Requires-Python: >=3.8
License-File: LICENSE
Requires-Dist: aiohttp>=3.8.0
Requires-Dist: python-dotenv>=0.19.0
Provides-Extra: dev
Requires-Dist: pytest>=7.0.0; extra == "dev"
Requires-Dist: pytest-asyncio>=0.21.0; extra == "dev"
Requires-Dist: pytest-cov>=4.0.0; extra == "dev"
Requires-Dist: black>=23.0.0; extra == "dev"
Requires-Dist: flake8>=6.0.0; extra == "dev"
Requires-Dist: mypy>=1.0.1; extra == "dev"
Dynamic: license-file
